CHANGELOG.txt
LICENCE.txt
MANIFEST.in
README.txt
setup.py
DocxpressoSDK/SDK.py
DocxpressoSDK/__init__.py
DocxpressoSDK.egg-info/PKG-INFO
DocxpressoSDK.egg-info/SOURCES.txt
DocxpressoSDK.egg-info/dependency_links.txt
DocxpressoSDK.egg-info/top_level.txt