Metadata-Version: 2.1
Name: DocxpressoSDK
Version: 1.0
Summary: SDK package
Home-page: https://docxpresso.com
Author: Docxpresso
Author-email: eduardo@docxpresso.com
License: MIT
Keywords: Docxpresso SDK
Classifier: Development Status :: 5 - Production/Stable
Classifier: Intended Audience :: Information Technology
Classifier: License :: OSI Approved :: MIT License
Classifier: Programming Language :: Python :: 3
License-File: LICENCE.txt
